gymnasium_sudoku/__init__.py
gymnasium_sudoku/environment.py
gymnasium_sudoku/puzzle.py
gymnasium_sudoku/rendering.py
gymnasium_sudoku/datasets/v0_biased/test_boards.csv
gymnasium_sudoku/datasets/v0_biased/train_boards.csv
gymnasium_sudoku/datasets/v1_easy/test_boards.csv
gymnasium_sudoku/datasets/v1_easy/train_boards.csv
gymnasium_sudoku-0.3.4.dist-info/licenses/LICENSE
gymnasium_sudoku-0.3.4.dist-info/METADATA
gymnasium_sudoku-0.3.4.dist-info/WHEEL
gymnasium_sudoku-0.3.4.dist-info/top_level.txt
gymnasium_sudoku-0.3.4.dist-info/RECORD
