Metadata-Version: 2.4
Name: gymnasium_sudoku
Version: 0.3.4
Summary: A Sudoku environment for Reinforcement Learning research
Author-email: adeottidev@gmail.com
License: The MIT License
Project-URL: Homepage, https://github.com/adeotti/Gymnasium-Sudoku
Project-URL: Repository, https://github.com/adeotti/Gymnasium-Sudoku
Keywords: Reinforcement Learning,game,RL,AI,gymnasium,Sudoku
Classifier: Development Status :: 3 - Alpha
Classifier: License :: OSI Approved :: MIT License
Classifier: Programming Language :: Python :: 3
Classifier: Programming Language :: Python :: 3.10
Classifier: Programming Language :: Python :: 3.11
Classifier: Intended Audience :: Science/Research
Classifier: Topic :: Scientific/Engineering :: Artificial Intelligence
Requires-Python: >=3.10
License-File: LICENSE
Requires-Dist: gymnasium>=1.1.1
Requires-Dist: numpy>=1.25.2
Requires-Dist: PySide6>=6.7.2
Requires-Dist: typing-extensions>=4.14.0
Requires-Dist: cloudpickle>=3.1.1
Requires-Dist: tqdm>=4.67.1
Requires-Dist: pathlib>=1.0.1
Dynamic: license-file
